RWAPIMicroservicePython/__init__.py
RWAPIMicroservicePython/cloudwatch.py
RWAPIMicroservicePython/errors.py
RWAPIMicroservicePython/main.py
RWAPIMicroservicePython/test_utils.py
RWAPIMicroservicePython-3.0.0.dist-info/LICENSE
RWAPIMicroservicePython-3.0.0.dist-info/METADATA
RWAPIMicroservicePython-3.0.0.dist-info/WHEEL
RWAPIMicroservicePython-3.0.0.dist-info/top_level.txt
RWAPIMicroservicePython-3.0.0.dist-info/RECORD
